coffeeshop/coffeeshop.py
coffeeshop-1.2.0.dist-info/LICENSE
coffeeshop-1.2.0.dist-info/METADATA
coffeeshop-1.2.0.dist-info/WHEEL
coffeeshop-1.2.0.dist-info/top_level.txt
coffeeshop-1.2.0.dist-info/RECORD
