Metadata-Version: 2.1
Name: coffeeshop
Version: 1.2.0
Summary: A python package that sends your deep learning training and validation metrics to your slack channel or user after every specified epoch.
Home-page: https://github.com/CleanPegasus/coffeeshop
Author: Arunkumar L - A roboVITics project
Author-email: arunk609@gmail.com
License: MIT
Platform: UNKNOWN
Classifier: Programming Language :: Python :: 3
Classifier: Programming Language :: Python :: 3.7
Requires-Dist: keras (>=2.2.0)
Requires-Dist: slackclient
